warp_md/__init__.py
warp_md/builder.py
warp_md/cli.py
warp_md/tests/test_cli_help.py
warp_md/traj_py.cpython-38-x86_64-linux-gnu.so
warp_md-0.1.0.dist-info/METADATA
warp_md-0.1.0.dist-info/WHEEL
warp_md-0.1.0.dist-info/entry_points.txt
warp_md-0.1.0.dist-info/licenses/LICENSE
warp_md-0.1.0.dist-info/RECORD
