Metadata-Version: 2.4
Name: warp-md
Version: 0.1.0
Requires-Dist: numpy
Requires-Dist: pyyaml ; extra == 'cli'
Provides-Extra: cli
License-File: LICENSE
Summary: warp-md Python bindings
Requires-Python: >=3.9
